{
  "signin_page": {
    "signin": "Логін",
    "signup": "Зареєструватися",
    "forgotPassword": "Забули пароль?",
    "forgot": "Забули",
    "account": "Не зареєструвалися?"
  },
  "signup_page": {
    "signup": "Зареєструватися",
    "signin": "Логін"
  },
  "auth_form": {
    "email": "Пошта",
    "password": "Пароль",
    "passwordEnter": "Введіть пароль",
    "emailEnter": "Введіть пошту",
    "verfpassword": "лист підтвердження",
    "send": "Відправити",
    "resend": "Надіслати повторно",
    "changePassword": "Змінити пароль",
    "repeatPassword": "Повторіть пароль"
  },
  "forgot_page": {
    "recoverPassword": "Відновлення паролю:"
  },
  "modals": {
    "waterAmount": "Кількість води",
    "recordingTime": "Записуємо час:",
    "enterWater": "Введіть кількість випитої води:",
    "saveBtn": "Зберегти",
    "addWater": "Додати води",
    "addWaterBtn": "Додати води",
    "chooseValue": "Виберіть значення",
    "editWater": "Відредагуйте введену кількість води",
    "correctData": "Правильно введені дані:",
    "sureDelete": "Ви впевнені, що хочете видалити запис?",
    "delete": "Видалити",
    "cancel":"Cкасувати",
    "deleteEntry": "Видалити запис",
    "logOut": "Вийти",
    "wantLeave":"Ви точно хочете вийти?"
  },
  "advantagesSection": {
    "our": "Наші",
    "happy": "",
    "customers": "користувачі",
    "HabitDrive": "Керування звичкою",
    "ViewStatistics": "Переглянути статистику",
    "PersonalRateSetting": "Індивідуальне встановлення норми"
  },
  
  "waterDailyNorma":{
    "dailyNorma":"Моя денна норма",
    "today":"Сьогодні"
  },
 
  "welcomeSection": {
    "recordDaily": "Записуйте та відстежуйте щоденне споживання води ",
    "waterTracker": "Трекер споживання води",
    "tryTracker":"Спробувати!"
  },
  "monthInfo":{
    "Month":"Місяць",
    "Statistics": "Статистика"
  }
  
}
